sunstone_rest_client/__init__.py
sunstone_rest_client/util.py
sunstone_rest_client-0.1.50.dist-info/DESCRIPTION.rst
sunstone_rest_client-0.1.50.dist-info/METADATA
sunstone_rest_client-0.1.50.dist-info/RECORD
sunstone_rest_client-0.1.50.dist-info/WHEEL
sunstone_rest_client-0.1.50.dist-info/metadata.json
sunstone_rest_client-0.1.50.dist-info/top_level.txt
sunstone_rest_client-0.1.50.dist-info/zip-safe
