Metadata-Version: 2.0
Name: sunstone-rest-client
Version: 0.1.50
Summary: sunstone rest client | an opennebula client in python, using the sunstone ReST API
Home-page: https://github.com/arnehilmann/sunstone-rest-client
Author: Arne Hilmann
Author-email: arne.hilmann@gmail.com
License: Apache License v2.0
Platform: UNKNOWN
Classifier: Development Status :: 3 - Alpha
Classifier: Programming Language :: Python
Requires-Dist: bs4
Requires-Dist: requests
